setup.py
f_luhn/__init__.py
f_luhn/f_luhn.py
f_luhn.egg-info/PKG-INFO
f_luhn.egg-info/SOURCES.txt
f_luhn.egg-info/dependency_links.txt
f_luhn.egg-info/top_level.txt