Metadata-Version: 1.0
Name: f-luhn
Version: 0.0.1
Summary: 一种连作者自己都看不明白的luhn校验码计算方案
Home-page: https://github.com/tjgo/f_luhn
Author: fangzhao
Author-email: elpmis.fang@qq.com
License: BSD License
Platform: all
